dalec/__init__.py
dalec/apps.py
dalec/models.py
dalec/proxy.py
dalec/settings.py
dalec/tests_utils.py
dalec/urls.py
dalec/views.py
dalec/locale/dalek/LC_MESSAGES/django.mo
dalec/locale/dalek/LC_MESSAGES/django.po
dalec/locale/en/LC_MESSAGES/django.mo
dalec/locale/en/LC_MESSAGES/django.po
dalec/locale/fr/LC_MESSAGES/django.mo
dalec/locale/fr/LC_MESSAGES/django.po
dalec/static/dalec/js/main.js
dalec/templates/dalec/default/item.html
dalec/templates/dalec/default/list.html
dalec/templatetags/__init__.py
dalec/templatetags/dalec.py
dalec_example/__init__.py
dalec_example/apps.py
dalec_example/proxy.py
dalec_example/templates/dalec/example/french_educ-item.html
dalec_example/templates/dalec/example/quarter-item.html
dalec_prime/__init__.py
dalec_prime/apps.py
dalec_prime/models.py
dalec_prime/migrations/0001_initial.py
dalec_prime/migrations/0001_squashed_0005_auto_20231017_1208.py
dalec_prime/migrations/0002_auto_20211109_1546.py
dalec_prime/migrations/0003_auto_20211109_1615.py
dalec_prime/migrations/0004_alter_content_id_alter_fetchhistory_id.py
dalec_prime/migrations/0005_auto_20231017_1208.py
dalec_prime/migrations/__init__.py
tests/__init__.py
tests/apps.py
tests/models.py
tests/settings.py
tests/tests.py
tests/urls.py
tests/proxies/__init__.py
tests/proxies/adiposian.py
tests/proxies/bad_wolf.py
tests/proxies/empty_child.py
tests/proxies/nice_dalek.py
dalec-0.2.8.dist-info/AUTHORS
dalec-0.2.8.dist-info/LICENSE
dalec-0.2.8.dist-info/METADATA
dalec-0.2.8.dist-info/WHEEL
dalec-0.2.8.dist-info/top_level.txt
dalec-0.2.8.dist-info/RECORD
