Metadata-Version: 2.1
Name: dalec
Version: 0.2.8
Summary: Extendable app to retrieve external contents from various external sources.
Home-page: https://github.com/webu/dalec
Author: Webu
Author-email: contact@webu.coop
License: BSD-3-Clause
Project-URL: Source, https://github.com/webu/dalec
Project-URL: Tracker, https://github.com/webu/dalec/issues
Classifier: Development Status :: 5 - Production/Stable
Classifier: Environment :: Web Environment
Classifier: Framework :: Django
Classifier: Intended Audience :: Developers
Classifier: License :: OSI Approved :: BSD License
Classifier: Operating System :: OS Independent
Classifier: Programming Language :: Python
Classifier: Programming Language :: Python :: 3
Classifier: Topic :: Internet :: WWW/HTTP
Classifier: Topic :: Internet :: WWW/HTTP :: Dynamic Content
Classifier: Topic :: Software Development :: Libraries :: Application Frameworks
Classifier: Topic :: Software Development :: Libraries :: Python Modules
Requires-Python: >=3.7
License-File: LICENSE
License-File: AUTHORS
Requires-Dist: Django >=2.2
Provides-Extra: testing
Requires-Dist: requests ; extra == 'testing'
Requires-Dist: beautifulsoup4 ; extra == 'testing'
Requires-Dist: coverage >=3.7.0 ; extra == 'testing'
Requires-Dist: black ; extra == 'testing'
Requires-Dist: flake8 ; extra == 'testing'
Requires-Dist: mypy ; extra == 'testing'
Requires-Dist: types-requests ; extra == 'testing'
